flascord/DiscordOauth2.py
flascord/__init__.py
flascord/scope.py
Flascord-0.1.1.dist-info/LICENSE
Flascord-0.1.1.dist-info/METADATA
Flascord-0.1.1.dist-info/WHEEL
Flascord-0.1.1.dist-info/top_level.txt
Flascord-0.1.1.dist-info/RECORD
