Metadata-Version: 2.1
Name: Flascord
Version: 0.1.1
Summary: UNKNOWN
Home-page: https://github.com/yorukaze-luru/Flascord
Author: Yorukaze LURU
License: MIT
Platform: UNKNOWN
Requires-Dist: Flask
Requires-Dist: requests
